reza/__init__.py
reza/_fallback.py
reza/_reza_cpp.cp311-win_amd64.pyd
reza_filter-0.2.5.dist-info/METADATA
reza_filter-0.2.5.dist-info/WHEEL
reza_filter-0.2.5.dist-info/licenses/LICENSE
reza_filter-0.2.5.dist-info/RECORD
