Metadata-Version: 2.1
Name: reza-filter
Version: 0.2.5
Summary: Reza exponential-window frequency-domain filter (NumPy FFT + C++/pybind11 acceleration).
Keywords: signal-processing,filter,EEG,IMU,gait,biomechanics
Author: Reza Pousti
License: MIT
Project-URL: Homepage, https://github.com/Rezapousti/Reza-Filter
Project-URL: Source, https://github.com/Rezapousti/Reza-Filter
Project-URL: Issues, https://github.com/Rezapousti/Reza-Filter/issues
Requires-Python: >=3.9
Requires-Dist: numpy<2.0,>=1.21
